README.md
setup.py
nlpcommon/__init__.py
nlpcommon/data.py
nlpcommon/log.py
nlpcommon/tokenizer.py
nlpcommon.egg-info/PKG-INFO
nlpcommon.egg-info/SOURCES.txt
nlpcommon.egg-info/dependency_links.txt
nlpcommon.egg-info/not-zip-safe
nlpcommon.egg-info/requires.txt
nlpcommon.egg-info/top_level.txt
nlpcommon/../LICENSE
nlpcommon/../README.md
nlpcommon/../requirements.txt
nlpcommon/data/sentence_symbol.txt
nlpcommon/data/stopwords.txt