Metadata-Version: 2.1
Name: nlpcommon
Version: 0.1.1
Summary: Common Tool for NLP
Home-page: https://github.com/shibing624/nlpcommon
Author: XuMing
Author-email: xuming624@qq.com
License: Apache 2.0
Keywords: nlpcommon,textclassifier,text tool
Platform: UNKNOWN
Classifier: Development Status :: 5 - Production/Stable
Classifier: Intended Audience :: Developers
Classifier: Intended Audience :: Education
Classifier: Intended Audience :: Science/Research
Classifier: License :: OSI Approved :: Apache Software License
Classifier: Operating System :: OS Independent
Classifier: Programming Language :: Python :: 3
Classifier: Programming Language :: Python :: 3.6
Classifier: Programming Language :: Python :: 3.7
Classifier: Programming Language :: Python :: 3.8
Classifier: Programming Language :: Python :: 3.9
Classifier: Topic :: Scientific/Engineering :: Artificial Intelligence
Requires-Python: >=3.6.0
